camera_person_2d_mapping/__init__.py
camera_person_2d_mapping/enums.py
camera_person_2d_mapping/factory.py
camera_person_2d_mapping/mathematics.py
camera_person_2d_mapping/models.py
camera_person_2d_mapping/util.py
camera_person_2d_mapping/detectors/__init__.py
camera_person_2d_mapping/detectors/faster_r_cnn.py
camera_person_2d_mapping/detectors/yolo_v3.py
camera_person_2d_mapping/mappers/__init__.py
camera_person_2d_mapping/mappers/coord_mapper.py
camera_person_2d_mapping/trackers/__init__.py
camera_person_2d_mapping/trackers/deep_sort/__init__.py
camera_person_2d_mapping/trackers/deep_sort/deep_sort.py
camera_person_2d_mapping/trackers/deep_sort/iou_matching.py
camera_person_2d_mapping/trackers/deep_sort/kalman_filter.py
camera_person_2d_mapping/trackers/deep_sort/linear_assignment.py
camera_person_2d_mapping/trackers/deep_sort/nn_matching.py
camera_person_2d_mapping/trackers/deep_sort/track.py
camera_person_2d_mapping/trackers/deep_sort/tracker.py
camera_person_2d_mapping/trackers/deep_sort/tracking_detection.py
camera_person_2d_mapping-0.0.14.dist-info/LICENSE
camera_person_2d_mapping-0.0.14.dist-info/METADATA
camera_person_2d_mapping-0.0.14.dist-info/WHEEL
camera_person_2d_mapping-0.0.14.dist-info/top_level.txt
camera_person_2d_mapping-0.0.14.dist-info/RECORD
