Metadata-Version: 2.1
Name: camera-person-2d-mapping
Version: 0.0.14
Summary: Python library for detecting and convertion people from survaillance camer footage to a 2D coordinate.
Home-page: UNKNOWN
Author: Me
License: MIT
Platform: UNKNOWN
License-File: LICENSE
Requires-Dist: opencv-python
Requires-Dist: numpy
Requires-Dist: tensorflow
Requires-Dist: scipy
Requires-Dist: scikit-image
